Metadata-Version: 2.1
Name: django-emailuser
Version: 1.1.2
Summary: emailuser, make email as username, But unique username also exists.
Home-page: https://github.com/Swe-HimelRana/django-email-user
Author: Himel Rana
Author-email: contact@himelrana-swe.com
License: MIT
Keywords: django,django emailuser,django email user,django email username,django email as username
Platform: UNKNOWN
Classifier: Development Status :: 5 - Production/Stable
Classifier: Intended Audience :: Developers
Classifier: Topic :: Software Development :: Libraries :: Python Modules
Classifier: License :: OSI Approved :: MIT License
Classifier: Programming Language :: Python :: 3
Classifier: Programming Language :: Python :: 3.4
Classifier: Programming Language :: Python :: 3.5
Classifier: Programming Language :: Python :: 3.6
Classifier: Programming Language :: Python :: 3.7
Classifier: Programming Language :: Python :: 3.8
Classifier: Operating System :: OS Independent
Classifier: Framework :: Django
Classifier: Framework :: Django :: 2.0
Classifier: Framework :: Django :: 2.1
Classifier: Framework :: Django :: 2.2
Classifier: Framework :: Django :: 3.0
